{
  "checklist": [
    {
      "id": 1,
      "item": "Customer Information",
      "search_entities": ["Customer Name", "Contact Details", "Company Type"],
      "removed_entities": [],
      "analysis_type": "Search & Highlight",
      "selected": true
    },
    {
      "id": 2,
      "item": "Project Location",
      "search_entities": ["Address", "City", "Country"],
      "removed_entities": [],
      "analysis_type": "Search & Highlight",
      "selected": true
    },
    {
      "id": 3,
      "item": "Installation Period",
      "search_entities": ["Timeline", "Deadline", "Milestone"],
      "removed_entities": [],
      "analysis_type": "Search & Highlight",
      "selected": true
    },
    {
      "id": 4,
      "item": "Liability Terms",
      "search_entities": ["Liability Limits", "Insurance Requirements"],
      "removed_entities": [],
      "analysis_type": "Search & Highlight",
      "selected": true
    },
    {
      "id": 5,
      "item": "Payment Terms",
      "search_entities": ["Payment Schedule", "Currency", "Tax Obligations"],
      "removed_entities": [],
      "analysis_type": "Search & Highlight",
      "selected": true
    }

  ],
  "variable_criteria": {
      "minimum_period": "3 weeks",
      "units": "Weeks",
      "maximum_liability": "100",
      "insurance_minimum": "$1 M USD"
  },
  "exemption_lists": {
      "project_type": "Standard Commercial",
      "regional": "Europe"
  }
} 